MoralisSDK/__init__.py
MoralisSDK/api.py
MoralisSDK/chainlink.py
MoralisSDK/ipfs.py
MoralisSDK/nft_storage/__init__.py
MoralisSDK/nft_storage/api_client.py
MoralisSDK/nft_storage/configuration.py
MoralisSDK/nft_storage/exceptions.py
MoralisSDK/nft_storage/model_utils.py
MoralisSDK/nft_storage/rest.py
MoralisSDK/nft_storage/api/__init__.py
MoralisSDK/nft_storage/api/nft_storage_api.py
MoralisSDK/nft_storage/apis/__init__.py
MoralisSDK/nft_storage/model/__init__.py
MoralisSDK/nft_storage/model/check_response.py
MoralisSDK/nft_storage/model/check_response_value.py
MoralisSDK/nft_storage/model/deal.py
MoralisSDK/nft_storage/model/delete_response.py
MoralisSDK/nft_storage/model/error_response.py
MoralisSDK/nft_storage/model/error_response_error.py
MoralisSDK/nft_storage/model/files.py
MoralisSDK/nft_storage/model/forbidden_error_response.py
MoralisSDK/nft_storage/model/forbidden_error_response_error.py
MoralisSDK/nft_storage/model/get_response.py
MoralisSDK/nft_storage/model/links.py
MoralisSDK/nft_storage/model/links_file.py
MoralisSDK/nft_storage/model/list_response.py
MoralisSDK/nft_storage/model/nft.py
MoralisSDK/nft_storage/model/pin.py
MoralisSDK/nft_storage/model/pin_status.py
MoralisSDK/nft_storage/model/unauthorized_error_response.py
MoralisSDK/nft_storage/model/unauthorized_error_response_error.py
MoralisSDK/nft_storage/model/upload_response.py
MoralisSDK/nft_storage/models/__init__.py
MoralisSDK-1.0.3.dist-info/METADATA
MoralisSDK-1.0.3.dist-info/WHEEL
MoralisSDK-1.0.3.dist-info/top_level.txt
MoralisSDK-1.0.3.dist-info/RECORD
