Metadata-Version: 2.1
Name: MoralisSDK
Version: 1.0.3
Summary: A python wrapper for the Molaris REST API
Home-page: https://github.com/kbm9696/MoralisSDK
Author: Balamurugan
Author-email: kbala007.1996@gmail.com
License: GNU General Public License v3.0
Keywords: MoralisSDK,Moralis package,ipfs SDK
Platform: UNKNOWN
Requires-Dist: requests
Requires-Dist: pinatapy-vourhey
Requires-Dist: python-dateutil
Requires-Dist: urllib3
